pwas/__init__.py
pwas/gene_effect_score_aggregation.py
pwas/genotype.py
pwas/statistics.py
pwas/shared_utils/__init__.py
pwas/shared_utils/reference_genome.py
pwas/shared_utils/util.py
pwas-1.0.2.data/scripts/calc_gene_effect_scores
pwas-1.0.2.data/scripts/combine_pwas_results
pwas-1.0.2.data/scripts/determine_ref_alleles
pwas-1.0.2.data/scripts/list_all_variants
pwas-1.0.2.data/scripts/organize_variant_effects_per_gene
pwas-1.0.2.data/scripts/pwas_test_genes
pwas-1.0.2.dist-info/METADATA
pwas-1.0.2.dist-info/WHEEL
pwas-1.0.2.dist-info/top_level.txt
pwas-1.0.2.dist-info/RECORD
