Metadata-Version: 2.1
Name: pwas
Version: 1.0.2
Summary: Proteome-Wide Association Study (PWAS) is a protein-centric, gene-based method for conducting genetic association studies.
Home-page: https://github.com/nadavbra/pwas
Author: Nadav Brandes
Author-email: nadav.brandes@mail.huji.ac.il
License: MIT
Platform: UNKNOWN
Requires-Dist: numpy
Requires-Dist: scipy
Requires-Dist: pandas
Requires-Dist: matplotlib
Requires-Dist: biopython
Requires-Dist: statsmodels
